README.md
setup.cfg
setup.py
states/__init__.py
states/callbacks.py
states/configuration.py
states/exception.py
states/machine.py
states/normalize.py
states/stateful.py
states/tools.py
states/transitions.py
states3.egg-info/PKG-INFO
states3.egg-info/SOURCES.txt
states3.egg-info/dependency_links.txt
states3.egg-info/top_level.txt